{"1": "cg_B_INST_13231", "2": "cg_B_INST_12585", "3": "cg_B_INST_12800", "4": "cg_B_INST_12449", "5": "cg_B_INST_12974", "6": "cg_B_INST_12582", "7": "cg_B_INST_12428", "8": "cg_B_INST_13234", "9": "cg_B_INST_13118", "10": "cg_B_INST_12910", "11": "cg_B_INST_13194", "12": "cg_B_INST_1588", "13": "cg_B_INST_12664", "14": "cg_B_INST_13246", "15": "cg_B_INST_13135", "16": "cg_B_INST_12508", "17": "cg_B_INST_12768", "18": "cg_B_INST_13013", "19": "cg_B_INST_12810", "20": "cg_B_INST_12691", "21": "cg_B_INST_12829", "22": "cg_B_INST_13235", "23": "cg_B_INST_1565", "24": "cg_B_INST_12478", "25": "cg_B_INST_1638", "26": "cg_B_INST_12984", "27": "cg_B_INST_1649", "28": "cg_B_INST_16436", "29": "cg_B_INST_12591", "30": "cg_B_INST_12692", "31": "cg_B_INST_13072", "32": "cg_B_INST_12356", "33": "cg_B_INST_12852", "34": "cg_B_INST_12847", "35": "cg_B_INST_12634", "36": "cg_B_INST_12423", "37": "cg_B_INST_12400", "38": "cg_B_INST_12656", "39": "cg_B_INST_1651", "40": "cg_B_INST_12727", "41": "cg_B_INST_12375", "42": "cg_B_INST_12884", "43": "cg_B_INST_12361", "44": "cg_B_INST_12407", "45": "cg_B_INST_13108", "46": "cg_B_INST_13077", "47": "cg_B_INST_13083", "48": "cg_B_INST_12791", "49": "cg_B_INST_12646", "50": "cg_B_INST_1563", "51": "cg_B_INST_12546", "52": "cg_B_INST_12606", "53": "cg_B_INST_13047", "54": "cg_B_INST_1595", "55": "cg_B_INST_13071", "56": "cg_B_INST_12824", "57": "cg_B_INST_12410", "58": "cg_B_INST_12688", "59": "cg_B_INST_13146", "60": "cg_B_INST_12411", "61": "cg_B_INST_13153", "62": "cg_B_INST_12789", "63": "cg_B_INST_12838", "64": "cg_B_INST_12563", "65": "cg_B_INST_12971", "66": "cg_B_INST_12383", "67": "cg_B_INST_12995", "68": "cg_B_INST_12363", "69": "cg_B_INST_12963", "70": "cg_B_INST_12977", "71": "cg_B_INST_12952", "72": "cg_B_INST_13155", "73": "cg_B_INST_12782", "74": "cg_B_INST_12588", "75": "cg_B_INST_12403", "76": "cg_B_INST_12886", "77": "cg_B_INST_12435", "78": "cg_B_INST_12704", "79": "cg_B_INST_12595", "80": "cg_B_INST_16437", "81": "cg_B_INST_1658", "82": "cg_B_INST_1643", "83": "cg_B_INST_13275", "84": "cg_B_INST_12562", "85": "cg_B_INST_13166", "86": "cg_B_INST_12778", "87": "cg_B_INST_12681", "88": "cg_B_INST_12463", "89": "cg_B_INST_13023", "90": "cg_B_INST_1601", "91": "cg_B_INST_1571", "92": "cg_B_INST_12887", "93": "cg_B_INST_12709", "94": "cg_B_INST_12771", "95": "cg_B_INST_12427", "96": "cg_B_INST_1700", "97": "cg_B_INST_12529", "98": "cg_B_INST_12392", "99": "cg_B_INST_12737", "100": "cg_B_INST_12624", "101": "cg_B_INST_12867", "102": "cg_B_INST_16434", "103": "cg_B_INST_12787", "104": "cg_B_INST_1574", "105": "cg_B_INST_12498", "106": "cg_B_INST_12497", "107": "cg_B_INST_16435", "108": "cg_B_INST_12650", "109": "cg_B_INST_12747", "110": "cg_B_INST_12817", "111": "cg_B_INST_12951", "112": "cg_B_INST_12474", "113": "cg_B_INST_12918", "114": "cg_B_INST_12708", "115": "cg_B_INST_12673", "116": "cg_B_INST_13240", "117": "cg_B_INST_12495", "118": "cg_B_INST_12521", "119": "cg_B_INST_12980", "120": "cg_B_INST_12369", "121": "cg_B_INST_12897", "122": "cg_B_INST_12947", "123": "cg_B_INST_12684", "124": "cg_B_INST_12574", "125": "cg_B_INST_12762", "126": "cg_B_INST_12558", "127": "cg_B_INST_1633", "128": "cg_B_INST_12798", "129": "cg_B_INST_12935", "130": "cg_B_INST_12359"}